cloakprompt/__init__.py
cloakprompt/cli.py
cloakprompt/config/regex_cleanup.yaml
cloakprompt/core/__init__.py
cloakprompt/core/parser.py
cloakprompt/core/redactor.py
cloakprompt/utils/__init__.py
cloakprompt/utils/file_loader.py
cloakprompt/utils/utils.py
cloakprompt-0.1.3.dist-info/licenses/LICENSE
cloakprompt-0.1.3.dist-info/METADATA
cloakprompt-0.1.3.dist-info/WHEEL
cloakprompt-0.1.3.dist-info/entry_points.txt
cloakprompt-0.1.3.dist-info/top_level.txt
cloakprompt-0.1.3.dist-info/RECORD
