Metadata-Version: 2.4
Name: cloakprompt
Version: 0.1.3
Summary: Secure text redaction for LLM interactions
Author-email: Kushagra Tandon <kushagra.tandon.124@gmail.com>
License: MIT
Project-URL: Homepage, https://github.com/Kushagratandon12/cloakprompt-cli
Project-URL: Documentation, https://github.com/Kushagratandon12/cloakprompt-cli#readme
Project-URL: Repository, https://github.com/Kushagratandon12/cloakprompt-cli
Project-URL: Bug Reports, https://github.com/Kushagratandon12/cloakprompt-cli/issues
Keywords: security,redaction,cli,llm,privacy,data-protection
Classifier: Development Status :: 4 - Beta
Classifier: Intended Audience :: Developers
Classifier: Intended Audience :: System Administrators
Classifier: License :: OSI Approved :: MIT License
Classifier: Operating System :: OS Independent
Classifier: Programming Language :: Python :: 3
Classifier: Programming Language :: Python :: 3.8
Classifier: Programming Language :: Python :: 3.9
Classifier: Programming Language :: Python :: 3.10
Classifier: Programming Language :: Python :: 3.11
Classifier: Programming Language :: Python :: 3.12
Classifier: Topic :: Security
Classifier: Topic :: Text Processing
Classifier: Topic :: Utilities
Requires-Python: >=3.8
License-File: LICENSE
Requires-Dist: typer>=0.9.0
Requires-Dist: PyYAML>=6.0
Requires-Dist: rich>=13.0.0
Provides-Extra: dev
Requires-Dist: pytest>=7.0.0; extra == "dev"
Requires-Dist: pytest-cov>=4.0.0; extra == "dev"
Requires-Dist: black>=23.0.0; extra == "dev"
Requires-Dist: flake8>=6.0.0; extra == "dev"
Requires-Dist: mypy>=1.0.0; extra == "dev"
Dynamic: license-file
